README.md
pyimpfuzzy.py
setup.py
bin/fuzzy.dll
bin/fuzzy64.dll
pyimpfuzzy_windows.egg-info/PKG-INFO
pyimpfuzzy_windows.egg-info/SOURCES.txt
pyimpfuzzy_windows.egg-info/dependency_links.txt
pyimpfuzzy_windows.egg-info/requires.txt
pyimpfuzzy_windows.egg-info/top_level.txt