Metadata-Version: 2.1
Name: pyimpfuzzy-windows
Version: 0.1
Summary: impfuzzy python modules for Windows
Home-page: https://github.com/JPCERTCC/impfuzzy/
Author: JPCERT/CC Analysis Center
Author-email: aa-info@jpcert.or.jp
License: the GNU General Public License version 2
Platform: UNKNOWN
